{
  "title": "PDF JPG 変換 無料 | Everything PDF",
  "metaDescription": "PDF JPG 変換を無料ですぐに。ファイルをアップロードせずブラウザ内で処理するので安全です。ページごとに画像として保存できます。",
  "h1": "PDF JPG 変換",
  "subtitle": "無料で、インストールも会員登録も不要、すぐに画像として保存できます。",
  "intro": "PDFをJPGやPNGの画像に変換して、チャット・ブログにそのまま載せましょう。プレゼン資料の1シーンを画像ファイルとして保存するときにも便利です。ファイルはお使いの端末内だけで処理するので安心してお使いください。",
  "steps": [
    "① 変換したいPDFファイルをアップします。",
    "② JPGかPNGの形式を選びます。",
    "③ 画質の倍率（1〜3倍）を決めます。",
    "④ 全体または希望のページを選びます。",
    "⑤ 変換ボタンを押して画像をダウンロードします。複数枚ならZIPで受け取れます。"
  ],
  "security": "変換はすべてブラウザ（端末）内で行われ、終わって画面を閉じるとすぐに消えます。だから契約書や行政手続きの書類のような機微な文書も、安心して画像に変換できます。",
  "faq": [
    {
      "q": "PNGにも変換できますか？",
      "a": "はい、形式でPNGを選べばOKです。JPGとPNGから好きな形式を選んで変換できます。一度に一つの形式で保存されます。"
    },
    {
      "q": "画質は保たれますか？",
      "a": "画質の倍率を上げると、より鮮明に出力されます。1倍は標準画質、2〜3倍に上げると文字や図がくっきりします。プレゼン資料をキャプチャするときや印刷するときは倍率を上げてみてください。"
    },
    {
      "q": "ページごとに1枚ずつ保存されますか？",
      "a": "はい、各ページが1枚の画像になります。複数枚ならZIPファイルにまとめて受け取り、1枚ならそのままダウンロードします。特定のページだけを選んで変換することもできます。"
    },
    {
      "q": "JPGとPNGのどちらを選べばいいですか？",
      "a": "透明な背景が必要だったり文字が多い文書はPNGがきれいです。容量を小さくしてチャット・ブログに軽く載せたいならJPGが良いです。ふだんの写真の共有はJPGで十分です。"
    },
    {
      "q": "ファイル数や容量の制限はありますか？",
      "a": "数や容量の制限はありません。透かしも入りません。ページの多いレポートも、そのまま画像に変換できます。"
    }
  ],
  "extraSections": [
    {
      "heading": "こんなときに便利です",
      "body": "課題やレポートの1ページをブログに移すとき、プレゼン資料の図表を画像としてキャプチャするとき、申込・契約書の特定のページをチャットで送るときに便利です。スマホからもその場で変換して、すぐに共有できます。"
    }
  ]
}
