{
  "title": "PDF 잠금해제 무료 | PDF의 모든 것",
  "metaDescription": "PDF 잠금해제를 무료로 하세요. 인쇄·편집 제한과 비밀번호를 풀어요. 파일은 내 기기에서만 처리해 서버로 올라가지 않습니다.",
  "h1": "PDF 잠금해제",
  "subtitle": "무료로, 설치 없이, 내 기기에서 바로 제한을 풀어요.",
  "intro": "내 PDF에 걸린 인쇄·편집 제한을 풉니다. 열 때 비밀번호를 묻는 문서는 아는 비밀번호를 넣고 풀어요. 파일은 브라우저 안에서만 처리해, 서버로 전송되지 않습니다.",
  "steps": [
    "① 잠금을 풀 PDF 파일을 올려요.",
    "② 인쇄·편집만 막힌 문서는 바로 제한이 풀려요.",
    "③ 열 때 비밀번호가 필요한 문서는 아는 비밀번호를 입력해요.",
    "④ '이미지로 해제'를 선택해 비밀번호를 제거해요.",
    "⑤ 잠금이 풀린 PDF를 내 기기에 저장해요."
  ],
  "security": "이 도구는 암호를 알아내는 크랙이 아니라, 본인이 아는 비밀번호나 인쇄·편집 제한을 제거하는 도구입니다. 모르는 비밀번호는 풀 수 없습니다. 파일과 입력한 비밀번호는 내 브라우저에서만 쓰이고, 서버로 저장·전송되지 않습니다.",
  "faq": [
    {
      "q": "비밀번호를 모르면 PDF 잠금을 풀 수 있나요?",
      "a": "아니요. 모르는 비밀번호는 풀 수 없습니다. 이 도구는 본인이 알고 있는 비밀번호를 제거하거나 인쇄·편집 제한을 푸는 도구이며, 암호 크랙이 아닙니다."
    },
    {
      "q": "입력한 비밀번호가 저장되거나 어딘가로 전송되나요?",
      "a": "아니요. 입력한 비밀번호는 내 브라우저 안에서만 쓰입니다. 서버로 저장되거나 전송되지 않으며, 작업이 끝나면 메모리에서 사라집니다."
    },
    {
      "q": "권한제한과 열람암호는 무엇이 다른가요?",
      "a": "권한제한은 문서는 열리지만 인쇄·편집·복사가 막힌 상태로, 비밀번호 없이 바로 풀 수 있습니다. 열람암호는 문서를 열 때부터 비밀번호를 묻는 잠금으로, 아는 비밀번호를 입력하고 '이미지로 해제'를 선택해 제거합니다."
    },
    {
      "q": "PDF 비밀번호 제거가 법적으로 문제 없나요?",
      "a": "본인 문서이거나 정당한 권한이 있는 문서의 제한을 푸는 용도라면 문제없습니다. 예를 들어 내가 받은 청약 안내서나 직접 만든 계약서·보고서의 인쇄 제한을 풀 때 쓰면 됩니다. 권한 없는 타인의 문서를 푸는 데 쓰면 안 됩니다."
    },
    {
      "q": "회원가입이나 프로그램 설치가 필요한가요?",
      "a": "아니요. 회원가입과 설치 없이 바로 쓸 수 있습니다. 완전 무료이며 워터마크가 붙지 않고, 파일 개수나 용량 제한도 없습니다."
    },
    {
      "q": "스캔본이나 민감한 계약서도 안전하게 풀 수 있나요?",
      "a": "네. 파일은 내 기기 브라우저에서만 처리하고 서버로 올리지 않아, 계약서·민원 서류·스캔본 같은 민감한 문서도 외부로 새지 않습니다. 외산 도구처럼 업로드 후 일정 시간 뒤 삭제하는 방식이 아니라, 애초에 업로드하지 않습니다."
    }
  ],
  "extraSections": [
    {
      "heading": "이럴 때 쓰면 좋아요",
      "body": "직접 만든 보고서나 과제 PDF의 인쇄·편집 제한을 풀어 다시 손볼 때, 메일로 받은 청약 안내서나 명세서를 인쇄해 보관할 때, 비밀번호를 알고 있는 내 계약서를 비밀번호 없이 열어 보고 싶을 때 쓰세요. 모두 본인이 권한을 가진 문서에 한합니다."
    },
    {
      "heading": "이미지로 해제할 때 알아두세요",
      "body": "열람암호가 걸린 문서를 '이미지로 해제'하면 각 페이지가 이미지로 바뀌어 비밀번호가 사라집니다. 이 방식은 문서가 그대로 보이지만, 처리 후에는 글자를 직접 선택·복사하거나 본문을 수정하기 어렵습니다. 원본 비밀번호 PDF는 따로 보관해 두는 편이 안전합니다."
    }
  ],
  "limits": [
    "암호를 알아내는 도구가 아닙니다. 본인이 아는 비밀번호를 풀거나 인쇄·편집 제한을 제거하는 용도입니다.",
    "비밀번호를 모르면 열 수 없습니다."
  ]
}